apistar_session_cookie.py
apistar_session_cookie-1.0.0.dist-info/DESCRIPTION.rst
apistar_session_cookie-1.0.0.dist-info/METADATA
apistar_session_cookie-1.0.0.dist-info/RECORD
apistar_session_cookie-1.0.0.dist-info/WHEEL
apistar_session_cookie-1.0.0.dist-info/metadata.json
apistar_session_cookie-1.0.0.dist-info/top_level.txt
apistar_session_cookie-1.0.0.dist-info/zip-safe
