Metadata-Version: 2.0
Name: apistar-session-cookie
Version: 1.0.0
Summary: Cookie based Sessions for Apistar.
Home-page: https://github.com/juancarlospaco/apistar-session-cookie
Author: Juan Carlos
Author-email: juancarlospaco@gmail.com
License: GPLv3+ LGPLv3+
Download-URL: https://github.com/juancarlospaco/apistar-session-cookie
Keywords: apistar,cookie,session,minimalism,python3
Platform: UNKNOWN
Classifier: Development Status :: 5 - Production/Stable
Classifier: Development Status :: 6 - Mature
Classifier: Environment :: Console
Classifier: Environment :: No Input/Output (Daemon)
Classifier: Environment :: Other Environment
Classifier: Intended Audience :: Developers
Classifier: Natural Language :: English
Classifier: License :: OSI Approved :: GNU General Public License (GPL)
Classifier: License :: OSI Approved :: GNU Library or Lesser General Public License (LGPL)
Classifier: License :: OSI Approved :: GNU Lesser General Public License v3 or later (LGPLv3+)
Classifier: License :: OSI Approved :: GNU General Public License v3 or later (GPLv3+)
Classifier: Operating System :: OS Independent
Classifier: Operating System :: POSIX :: Linux
Classifier: Operating System :: Microsoft :: Windows
Classifier: Operating System :: MacOS :: MacOS X
Classifier: Programming Language :: Python
Classifier: Programming Language :: Python :: 3
Classifier: Programming Language :: Python :: 3 :: Only
Classifier: Programming Language :: Python :: 3.6
Classifier: Programming Language :: Python :: Implementation :: CPython
Classifier: Topic :: Software Development
Classifier: Topic :: Software Development :: Libraries
Requires: apistar
Requires-Python: >=3.6
Requires-Dist: apistar
